yaml_serialize/yaml_serialize.py
yaml_serialize-0.1.dist-info/METADATA
yaml_serialize-0.1.dist-info/WHEEL
yaml_serialize-0.1.dist-info/top_level.txt
yaml_serialize-0.1.dist-info/RECORD
