Metadata-Version: 2.1
Name: yaml-serialize
Version: 0.1
Summary: A simple way to store python objects in yaml
Home-page: https://github.com/JakeRoggenbuck/yaml_serialize
Author: Jake Roggenbuck
Author-email: jake@jr0.org
License: MIT
Platform: UNKNOWN
